.gitignore
LICENSE
README.rst
setup.cfg
setup.py
xdh/__init__.py
xdh/_dice.py
xdh/dice.py
xdh_dice.egg-info/PKG-INFO
xdh_dice.egg-info/SOURCES.txt
xdh_dice.egg-info/dependency_links.txt
xdh_dice.egg-info/requires.txt
xdh_dice.egg-info/top_level.txt